CONTRIBUTORS
LICENSE
README.rst
pyproject.toml
pyrh/__init__.py
pyrh/cache.py
pyrh/exceptions.py
pyrh/models/__init__.py
pyrh/models/base.py
pyrh/models/instrument.py
pyrh/models/oauth.py
pyrh/models/portfolio.py
pyrh/models/sessionmanager.py
pyrh/robinhood.py
pyrh/trade_history_downloader.py
pyrh/urls.py
pyrh-2.1.1.dist-info/LICENSE
pyrh-2.1.1.dist-info/WHEEL
pyrh-2.1.1.dist-info/METADATA
pyrh-2.1.1.dist-info/RECORD
