Metadata-Version: 2.1
Name: pyrh
Version: 2.1.1
Summary: Unofficial Robinhood Python API
Home-page: https://pyrh.readthedocs.io/en/latest
License: MIT
Keywords: trading,options,robinhood,stock,api
Author: Unofficial Robinhood Python API Developers
Requires-Python: >=3.8.1,<4.0.0
Classifier: License :: OSI Approved :: MIT License
Classifier: Programming Language :: Python :: 3
Classifier: Programming Language :: Python :: 3.9
Classifier: Programming Language :: Python :: 3.10
Classifier: Programming Language :: Python :: 3.11
Provides-Extra: docs
Provides-Extra: notebook
Requires-Dist: autodocsumm (>=0.2.9,<0.3.0) ; extra == "docs"
Requires-Dist: certifi (>=2020.4.5,<2021.0.0)
Requires-Dist: marshmallow (>=3.5.1,<4.0.0)
Requires-Dist: notebook (>=6.0.3,<7.0.0) ; extra == "notebook"
Requires-Dist: pyotp (>=2.7.0,<3.0.0)
Requires-Dist: python-dateutil (>=2.8,<3.0)
Requires-Dist: python-dotenv (>=0.13.0,<0.14.0) ; extra == "notebook"
Requires-Dist: pytz (>=2019.3,<2020.0)
Requires-Dist: requests (>=2.23,<3.0)
Requires-Dist: sphinx (>=5.3.0,<6.0.0) ; extra == "docs"
Requires-Dist: sphinx-autodoc-typehints (>=1.19.5,<2.0.0) ; extra == "docs"
Requires-Dist: sphinx_rtd_theme (>=1.1.1,<2.0.0) ; extra == "docs"
Requires-Dist: yarl (>=1.4.2,<2.0.0)
Project-URL: Repository, https://pyrh.readthedocs.io/en/latest
